cc_liquid/__init__.py
cc_liquid/backtester.py
cc_liquid/callbacks.py
cc_liquid/cli.py
cc_liquid/cli_callbacks.py
cc_liquid/cli_display.py
cc_liquid/completion.py
cc_liquid/config.py
cc_liquid/data_loader.py
cc_liquid/py.typed
cc_liquid/trader.py
cc_liquid/portfolio/__init__.py
cc_liquid/portfolio/sizing.py
cc_liquid-0.1.8a8.dist-info/METADATA
cc_liquid-0.1.8a8.dist-info/WHEEL
cc_liquid-0.1.8a8.dist-info/entry_points.txt
cc_liquid-0.1.8a8.dist-info/licenses/LICENSE
cc_liquid-0.1.8a8.dist-info/RECORD
