Metadata-Version: 2.4
Name: cc-liquid
Version: 0.1.8a8
Summary: cc-liquid - open source reference implementation for a simple, metamodel-based Hyperliquid portfolio rebalancer
Author-email: CrowdCent <info@crowdcent.com>
License: MIT
License-File: LICENSE
Requires-Python: >=3.10
Requires-Dist: click>=8.1.8
Requires-Dist: crowdcent-challenge>=0.1.10
Requires-Dist: eth-account>=0.13.0
Requires-Dist: hyperliquid-python-sdk>=0.8.0
Requires-Dist: plotext>=5.3.2
Requires-Dist: polars>=1.0.0
Requires-Dist: python-dotenv>=1.1.0
Requires-Dist: pyyaml
Requires-Dist: requests>=2.32.3
Requires-Dist: rich>=13.7.1
Provides-Extra: numerai
Requires-Dist: numerapi==2.20.7; extra == 'numerai'
